{
  "props": {
    "pageProps": {
      "appDetails": {
        "id": 833,
        "access": "unrestricted",
        "approved": true,
        "categories": [
          "it_operations_management",
          "utilities"
        ],
        "contributors": [],
        "collections": [],
        "contact_email": "",
        "contact_notes": "",
        "contact_notes_source": "",
        "display_author": {
          "isPartner": false,
          "name": "Splunk LLC",
          "redirectTo": "Splunk"
        },
        "description": "*** Important: Read upgrade Instructions and test add-on update before deploying to production ***\nThere are changes to default indexes and .conf changes in version 6.0 of Splunk Add-on for Unix and Linux that can break an existing installation if upgrade instructions are not followed in detail. If an existing Splunk Add-on for Unix and Linux is being upgraded, please test in a non-production environment first.\n\n\nThe Splunk Add-on for Unix and Linux works with the Splunk App for Unix and Linux to provide rapid insights and operational visibility into large-scale Unix and Linux environments.  With its new pre-packaged alerting capability, flexible service-based hosts grouping, and easy management of many data sources, it arms administrators with a powerful ability to quickly identify performance and capacity bottlenecks and outliers in Unix and Linux environments.",
        "documentation": "<p>To learn about the Splunk Add-on for Unix and Linux, see the official documentation here on <a href=\"http://docs.splunk.com/Documentation/AddOns/released/UnixLinux/About\">docs.splunk.com</a>.</p>\n<p>For information on what has been fixed as well as known issues, see the <a href=\"http://docs.splunk.com/Documentation/AddOns/released/UnixLinux/Releasenotes\">release notes</a>.</p>",
        "documentation_source": "To learn about the Splunk Add-on for Unix and Linux, see the official documentation here on [docs.splunk.com](http://docs.splunk.com/Documentation/AddOns/released/UnixLinux/About).\r\n\r\nFor information on what has been fixed as well as known issues, see the [release notes](http://docs.splunk.com/Documentation/AddOns/released/UnixLinux/Releasenotes).",
        "download_count": 406859,
        "icon": "https://cdn.splunkbase.splunk.com/media/public/icons/084e0458-23fb-11f0-8ff1-0e7fb705666c.png",
        "inquiry_buttontext": "",
        "inquiry_url": "",
        "is_archived": false,
        "is_directory_listing": false,
        "is_soar_certified": false,
        "is_splunk_built": true,
        "installation": "",
        "installation_source": "",
        "license": {
          "canonical_name": "Splunk General Terms",
          "display_name": "Splunk General Terms",
          "url": "https://www.splunk.com/en_us/legal/splunk-general-terms.html"
        },
        "license_name": "Splunk General Terms",
        "license_url": "https://www.splunk.com/en_us/legal/splunk-general-terms.html",
        "license_agreement_read_required": false,
        "product": "splunk",
        "product_types": [
          "enterprise",
          "cloud",
          "itsi"
        ],
        "public": true,
        "ranking": [
          {
            "rank": 1,
            "category_name": "utilities",
            "category_display_name": "Utilities"
          },
          {
            "rank": 5,
            "category_name": "it_operations_management",
            "category_display_name": "IT Operations"
          }
        ],
        "rating": {
          "count": 56,
          "average": 3
        },
        "release": {
          "actions": [],
          "cim_compatibility": [
            "4.x"
          ],
          "cloud_compatible": true,
          "fedramp_validation": "no",
          "filename": "splunk-add-on-for-unix-and-linux_1010.tgz",
          "id": 37592,
          "md5": "e2d7dedbb2d9c94cb55f126d295cda0d",
          "min_product_version_str": null,
          "name": "10.1.0",
          "passed_validation": true,
          "path": "https://splunkbase.splunk.com/app/833/release/10.1.0/download/",
          "platform": "independent",
          "product_types": [
            "enterprise",
            "cloud"
          ],
          "public_ever_true": false,
          "published_datetime": "2025-04-28T06:58:45.300659Z",
          "release_notes": "",
          "sha256": "67c8471e6b8c5d7aea3eff3f351b61cfaed5ad2eca2a9b22d9959ee0a0efd3f8",
          "signed_available": true,
          "size": 134865,
          "updated_datetime": "2025-06-21T05:47:50.830797Z",
          "version_compatibility": [
            "10.0",
            "9.4",
            "9.3",
            "9.2",
            "9.1"
          ]
        },
        "releases": [
          {
            "actions": [],
            "cim_compatibility": [
              "4.x"
            ],
            "cloud_compatible": true,
            "fedramp_validation": "no",
            "filename": "splunk-add-on-for-unix-and-linux_1010.tgz",
            "id": 37592,
            "md5": "e2d7dedbb2d9c94cb55f126d295cda0d",
            "min_product_version_str": null,
            "name": "10.1.0",
            "passed_validation": true,
            "path": "https://splunkbase.splunk.com/app/833/release/10.1.0/download/",
            "platform": "independent",
            "product_types": [
              "enterprise",
              "cloud"
            ],
            "public_ever_true": false,
            "published_datetime": "2025-04-28T06:58:45.300659Z",
            "release_notes": "",
            "sha256": "67c8471e6b8c5d7aea3eff3f351b61cfaed5ad2eca2a9b22d9959ee0a0efd3f8",
            "signed_available": true,
            "size": 134865,
            "updated_datetime": "2025-06-21T05:47:50.830797Z",
            "version_compatibility": [
              "10.0",
              "9.4",
              "9.3",
              "9.2",
              "9.1"
            ]
          }
        ],
        "repo_name": "",
        "repo_url": "",
        "screenshots": [],
        "support": "splunk",
        "title": "Splunk Add-on for Unix and Linux",
        "troubleshooting": "",
        "troubleshooting_source": "",
        "type": "addon",
        "updated_time": "2025-07-16T10:39:53.985322Z",
        "video_link": null,
        "app_type": "addon",
        "schedule_release": null,
        "name": "Splunk Add-on for Unix and Linux",
        "published_datetime": "2011-11-08T00:14:10Z",
        "draft": false,
        "display_editors": false
      }
    },
    "__N_SSP": true
  },
  "page": "/app/[id]",
  "query": {
    "id": "833"
  },
  "buildId": "Rl3dJ2Ba6-Z3dwWjnzfKA",
  "assetPrefix": "https://cdn.splunkbase.splunk.com",
  "isFallback": false,
  "isExperimentalCompile": false,
  "gssp": true,
  "scriptLoader": []
}